[
{"west": "\u0710\u0730\u0720\u0733\u0717\u0733\u0710", "audio_west": "http://www.sfarmele.de/audio/audio_wortliste/aloho.mp3", "phonetic_west": "aloho"},
{"west": "\u0721\u0733\u072a\u071d\u0733\u0710", "audio_west": "http://www.sfarmele.de/audio/audio_wortliste/moryo.mp3", "phonetic_west": "moryo"},
{"west": "\u0721\u0733\u072a\u0730\u0722", "audio_west": "http://www.sfarmele.de/audio/audio_wortliste/moran.mp3", "phonetic_west": "moran"},
{"west": "\u0721\u0733\u072a\u071d\u0733\u0710 \u0710\u0730\u0720\u0733\u0717\u0733\u0710", "audio_west": "http://www.sfarmele.de/audio/audio_wortliste/moryo aloho.mp3", "phonetic_west": "moryo aloho"},
{"west": "\u0710\u0730\u0720\u0733\u0717\u0733\u0710", "audio_west": "http://www.sfarmele.de/audio/audio_wortliste/aloho.mp3", "phonetic_west": "aloho"},
{"west": "\u0710\u073a\u071d\u0720", "audio_west": null, "phonetic_west": "il"},
{"west": "\u0721\u0733\u072a\u0733\u0710 \u0715\u071f\u073d\u0720", "audio_west": null, "phonetic_west": "moro d`kul"}
]