[
{"west": "\u0722\u0736\u0723\u071d\u073d\u0718\u0722\u0733\u0710", "audio_west": "http://www.sfarmele.de/audio/audio_wortliste/nesyuno.mp3", "phonetic_west": "nesyuno"},
{"west": "\u0722\u0736\u0723\u071d\u0733\u0722\u0733\u0710", "audio_west": "http://www.sfarmele.de/audio/audio_wortliste/nesyono.mp3", "phonetic_west": "nesyono"},
{"west": "\u0722\u0736\u0723\u071d\u073d\u0718\u0722\u0733\u0710", "audio_west": "http://www.sfarmele.de/audio/audio_wortliste/nesyuno.mp3", "phonetic_west": "nesyuno"}
]